./.gitignore
./PKG-INFO
./README.md
./pyproject.toml
./vision_agents/plugins/anthropic/__init__.py
./vision_agents/plugins/anthropic/anthropic_llm.py
./vision_agents/plugins/anthropic/events.py
vision_agents_plugins_anthropic-0.2.10.dist-info/METADATA
vision_agents_plugins_anthropic-0.2.10.dist-info/WHEEL
vision_agents_plugins_anthropic-0.2.10.dist-info/RECORD
