Metadata-Version: 2.4
Name: vision-agents-plugins-anthropic
Version: 0.2.10
Summary: Anthropic/Claude LLM integration for Vision Agents
Project-URL: Documentation, https://visionagents.ai/
Project-URL: Website, https://visionagents.ai/
Project-URL: Source, https://github.com/GetStream/Vision-Agents
License-Expression: MIT
Keywords: AI,LLM,agents,anthropic,claude,voice agents
Requires-Python: >=3.10
Requires-Dist: anthropic
Requires-Dist: vision-agents
